brutefeedparser/__init__.py
brutefeedparser/brutefeedparser.py
brutefeedparser-0.10.5.dist-info/LICENSE
brutefeedparser-0.10.5.dist-info/METADATA
brutefeedparser-0.10.5.dist-info/WHEEL
brutefeedparser-0.10.5.dist-info/RECORD
