Metadata-Version: 2.1
Name: brutefeedparser
Version: 0.10.5
Summary: Brute Feed Parser
License: GPL3
Author: Iwan Grozny
Author-email: renegat@renegat0x0.ddns.net
Requires-Python: >=3.9,<4.0
Classifier: License :: Other/Proprietary License
Classifier: Programming Language :: Python :: 3
Classifier: Programming Language :: Python :: 3.9
Classifier: Programming Language :: Python :: 3.10
Classifier: Programming Language :: Python :: 3.11
Classifier: Programming Language :: Python :: 3.12
Requires-Dist: beautifulsoup4 (>=4.13.3,<5.0.0)
Requires-Dist: lxml (>=5.3.0,<6.0.0)
